{
  "fetched_at": "2026-01-27T02:31:47.892668+00:00",
  "window_hours": 72,
  "score": 4.2,
  "risk_level": "LOW",
  "components": {
    "conflict_intensity": 8.5,
    "civilian_risk": 0.0
  },
  "weights": {
    "conflict_intensity": 0.5,
    "civilian_risk": 0.2
  },
  "items_count": 1,
  "sources": [
    {
      "name": "ReliefWeb - Mali",
      "url": "https://reliefweb.int/rss?search=country%3AMali",
      "status": "unreachable",
      "items": 0
    },
    {
      "name": "ReliefWeb - Niger",
      "url": "https://reliefweb.int/rss?search=country%3ANiger",
      "status": "unreachable",
      "items": 0
    },
    {
      "name": "ReliefWeb - Burkina Faso",
      "url": "https://reliefweb.int/rss?search=country%3ABurkina%20Faso",
      "status": "unreachable",
      "items": 0
    },
    {
      "name": "MaliWeb",
      "url": "https://www.maliweb.net/feed",
      "status": "ok",
      "items": 12
    },
    {
      "name": "LeFaso",
      "url": "https://lefaso.net/spip.php?page=backend",
      "status": "ok",
      "items": 48
    },
    {
      "name": "ActuNiger",
      "url": "https://www.actuniger.com/feed/",
      "status": "ok",
      "items": 5
    },
    {
      "name": "BBC Africa",
      "url": "https://feeds.bbci.co.uk/news/world/africa/rss.xml",
      "status": "ok",
      "items": 30
    },
    {
      "name": "UN News Africa",
      "url": "https://news.un.org/feed/subscribe/en/news/region/africa/feed/rss.xml",
      "status": "ok",
      "items": 30
    },
    {
      "name": "Crisis Group",
      "url": "https://www.crisisgroup.org/rss.xml",
      "status": "ok",
      "items": 10
    },
    {
      "name": "France 24 - Africa",
      "url": "https://www.france24.com/en/africa/rss",
      "status": "ok",
      "items": 30
    },
    {
      "name": "AllAfrica - Mali",
      "url": "https://allafrica.com/tools/headlines/rdf/mali/headlines.rdf",
      "status": "ok",
      "items": 19
    },
    {
      "name": "AllAfrica - Niger",
      "url": "https://allafrica.com/tools/headlines/rdf/niger/headlines.rdf",
      "status": "ok",
      "items": 4
    },
    {
      "name": "AllAfrica - Burkina Faso",
      "url": "https://allafrica.com/tools/headlines/rdf/burkinafaso/headlines.rdf",
      "status": "ok",
      "items": 10
    }
  ],
  "top_headlines": [
    {
      "title": "US to step up coordination with Nigeria to pursue Islamic State group militants",
      "link": "https://www.france24.com/en/africa/20260126-us-steps-up-cooperation-with-nigeria-to-pursue-islamic-state-group-militants",
      "source": "France 24 - Africa",
      "published_at": "2026-01-26T06:49:27+00:00",
      "score": 0.71,
      "tags": [
        "conflict_intensity"
      ],
      "regions": [
        "mali",
        "niger",
        "burkina",
        "burkina faso"
      ]
    }
  ],
  "forecast": [
    {
      "timestamp": "2026-01-27T05:31:32.877906+00:00",
      "score": 12.0
    },
    {
      "timestamp": "2026-01-27T08:31:17.863144+00:00",
      "score": 11.4
    },
    {
      "timestamp": "2026-01-27T11:31:02.848382+00:00",
      "score": 10.8
    },
    {
      "timestamp": "2026-01-27T14:30:47.833620+00:00",
      "score": 10.2
    },
    {
      "timestamp": "2026-01-27T17:30:32.818858+00:00",
      "score": 9.6
    },
    {
      "timestamp": "2026-01-27T20:30:17.804096+00:00",
      "score": 9.0
    }
  ]
}